klokku_python_client/__init__.py
klokku_python_client/api_client.py
klokku_python_client-0.5.1.dist-info/LICENSE
klokku_python_client-0.5.1.dist-info/METADATA
klokku_python_client-0.5.1.dist-info/WHEEL
klokku_python_client-0.5.1.dist-info/RECORD
