Metadata-Version: 2.3
Name: klokku-python-client
Version: 0.5.1
Summary: Klokku REST API client
License: MIT
Author: Mariusz Józala
Requires-Python: >=3.13
Classifier: Development Status :: 4 - Beta
Classifier: Intended Audience :: Developers
Requires-Dist: aiohttp (>=3.12.14,<4.0.0)
Project-URL: Homepage, https://klokku.com
Project-URL: Issues, https://github.com/klokku/klokku-python-client/issues
Project-URL: Repository, https://github.com/klokku/klokku-python-client
